MANIFEST.in
README.md
setup.py
include/lib_lob.hpp
include/limit_order_book.hpp
include/limit_tree.hpp
include/structures.hpp
limit_order_book/__init__.py
limit_order_book/library.py
limit_order_book/limit_order_book.py
limit_order_book.egg-info/PKG-INFO
limit_order_book.egg-info/SOURCES.txt
limit_order_book.egg-info/dependency_links.txt
limit_order_book.egg-info/not-zip-safe
limit_order_book.egg-info/top_level.txt
limit_order_book/test/__init__.py
limit_order_book/test/test_limit_order_book.py
src/lib_lob.cpp
vendor/Catch2/.gitattributes
vendor/Catch2/.gitignore
vendor/Catch2/.travis.yml
vendor/Catch2/CMakeLists.txt
vendor/Catch2/CODE_OF_CONDUCT.md
vendor/Catch2/LICENSE.txt
vendor/Catch2/README.md
vendor/Catch2/appveyor.yml
vendor/Catch2/codecov.yml
vendor/Catch2/conanfile.py
vendor/Catch2/.conan/build.py
vendor/Catch2/.conan/test_package/CMakeLists.txt
vendor/Catch2/.conan/test_package/conanfile.py
vendor/Catch2/.conan/test_package/test_package.cpp
vendor/Catch2/.github/FUNDING.yml
vendor/Catch2/.github/pull_request_template.md
vendor/Catch2/.github/ISSUE_TEMPLATE/bug_report.md
vendor/Catch2/.github/ISSUE_TEMPLATE/feature_request.md
vendor/Catch2/CMake/Catch2Config.cmake.in
vendor/Catch2/CMake/FindGcov.cmake
vendor/Catch2/CMake/FindLcov.cmake
vendor/Catch2/CMake/Findcodecov.cmake
vendor/Catch2/CMake/MiscFunctions.cmake
vendor/Catch2/CMake/catch2.pc.in
vendor/Catch2/CMake/llvm-cov-wrapper
vendor/Catch2/artwork/catch2-c-logo.png
vendor/Catch2/artwork/catch2-hand-logo.png
vendor/Catch2/artwork/catch2-logo-small.png
vendor/Catch2/contrib/Catch.cmake
vendor/Catch2/contrib/CatchAddTests.cmake
vendor/Catch2/contrib/ParseAndAddCatchTests.cmake
vendor/Catch2/contrib/gdbinit
vendor/Catch2/contrib/lldbinit
vendor/Catch2/docs/Readme.md
vendor/Catch2/docs/assertions.md
vendor/Catch2/docs/benchmarks.md
vendor/Catch2/docs/ci-and-misc.md
vendor/Catch2/docs/cmake-integration.md
vendor/Catch2/docs/command-line.md
vendor/Catch2/docs/commercial-users.md
vendor/Catch2/docs/configuration.md
vendor/Catch2/docs/contributing.md
vendor/Catch2/docs/deprecations.md
vendor/Catch2/docs/event-listeners.md
vendor/Catch2/docs/generators.md
vendor/Catch2/docs/limitations.md
